streamsx/mqtt/__init__.py
streamsx/mqtt/_mqtt.py
streamsx.mqtt-1.0.3.dist-info/LICENSE.txt
streamsx.mqtt-1.0.3.dist-info/METADATA
streamsx.mqtt-1.0.3.dist-info/WHEEL
streamsx.mqtt-1.0.3.dist-info/top_level.txt
streamsx.mqtt-1.0.3.dist-info/RECORD
