Metadata-Version: 2.1
Name: streamsx.mqtt
Version: 1.0.3
Summary: MQTT integration for IBM Streams topology applications
Home-page: https://github.com/IBMStreams/pypi.streamsx.mqtt
Author: IBM Streams @ github.com
Author-email: rolef.heinrich@de.ibm.com
License: Apache License - Version 2.0
Keywords: streams,ibmstreams,streaming,analytics,streaming-analytics,mqtt
Platform: UNKNOWN
Classifier: Development Status :: 4 - Beta
Classifier: License :: OSI Approved :: Apache Software License
Classifier: Programming Language :: Python :: 3
Classifier: Programming Language :: Python :: 3.5
Classifier: Programming Language :: Python :: 3.6
Classifier: Programming Language :: Python :: 3.7
Requires-Dist: streamsx (>=1.14.6)
Requires-Dist: streamsx.toolkits (>=1.2.0)
